{ "file": "procps/build/include/proc/alloc.h", "line": "11", "kind": "ParmDecl", "name": "size", "function": "c:@F@xcalloc", "type": { "type_name": "unsigned int", "type_usr": "", "type_is_pointer": false} }
{ "file": "procps/build/include/proc/alloc.h", "line": "12", "kind": "ParmDecl", "name": "size", "function": "c:@F@xmalloc", "type": { "type_name": "int", "type_usr": "", "type_is_pointer": false} }
{ "file": "procps/build/include/proc/alloc.h", "line": "13", "kind": "ParmDecl", "name": "oldp", "function": "c:@F@xrealloc", "type": { "type_name": "void *", "type_usr": "", "type_is_pointer": true, "pointee_type_name": "void", "pointee_type_usr": ""} }
{ "file": "procps/build/include/proc/alloc.h", "line": "13", "kind": "ParmDecl", "name": "size", "function": "c:@F@xrealloc", "type": { "type_name": "unsigned int", "type_usr": "", "type_is_pointer": false} }
{ "file": "procps/build/include/proc/alloc.h", "line": "14", "kind": "ParmDecl", "name": "str", "function": "c:@F@xstrdup", "type": { "type_name": "const char *", "type_usr": "", "type_is_pointer": true, "pointee_type_name": "const char", "pointee_type_usr": ""} }
{ "file": "procps/build/include/proc/devname.h", "line": "13", "kind": "ParmDecl", "name": "ret", "function": "c:@F@dev_to_tty", "type": { "type_name": "char *restrict", "type_usr": "", "type_is_pointer": true, "pointee_type_name": "char", "pointee_type_usr": ""} }
{ "file": "procps/build/include/proc/devname.h", "line": "13", "kind": "ParmDecl", "name": "chop", "function": "c:@F@dev_to_tty", "type": { "type_name": "unsigned int", "type_usr": "", "type_is_pointer": false} }
{ "file": "procps/build/include/proc/devname.h", "line": "13", "kind": "ParmDecl", "name": "dev_t_dev", "function": "c:@F@dev_to_tty", "type": { "type_name": "dev_t", "type_usr": "c:@T@dev_t", "type_is_pointer": false} }
{ "file": "procps/build/include/proc/devname.h", "line": "13", "kind": "ParmDecl", "name": "pid", "function": "c:@F@dev_to_tty", "type": { "type_name": "int", "type_usr": "", "type_is_pointer": false} }
{ "file": "procps/build/include/proc/devname.h", "line": "13", "kind": "ParmDecl", "name": "flags", "function": "c:@F@dev_to_tty", "type": { "type_name": "unsigned int", "type_usr": "", "type_is_pointer": false} }
{ "file": "procps/build/include/proc/devname.h", "line": "15", "kind": "ParmDecl", "name": "name", "function": "c:@F@tty_to_dev", "type": { "type_name": "const char *const restrict", "type_usr": "", "type_is_pointer": true, "pointee_type_name": "const char", "pointee_type_usr": ""} }
{ "file": "procps/build/include/proc/escape.h", "line": "17", "kind": "ParmDecl", "name": "dst", "function": "c:@F@escape_strlist", "type": { "type_name": "char *restrict", "type_usr": "", "type_is_pointer": true, "pointee_type_name": "char", "pointee_type_usr": ""} }
{ "file": "procps/build/include/proc/escape.h", "line": "17", "kind": "ParmDecl", "name": "src", "function": "c:@F@escape_strlist", "type": { "type_name": "char *const restrict *restrict", "type_usr": "", "type_is_pointer": true, "pointee_type_name": "char *const restrict", "pointee_type_usr": ""} }
{ "file": "procps/build/include/proc/escape.h", "line": "17", "kind": "ParmDecl", "name": "n", "function": "c:@F@escape_strlist", "type": { "type_name": "size_t", "type_usr": "c:@T@size_t", "type_is_pointer": false} }
{ "file": "procps/build/include/proc/escape.h", "line": "17", "kind": "ParmDecl", "name": "cells", "function": "c:@F@escape_strlist", "type": { "type_name": "int *", "type_usr": "", "type_is_pointer": true, "pointee_type_name": "int", "pointee_type_usr": ""} }
{ "file": "procps/build/include/proc/escape.h", "line": "18", "kind": "ParmDecl", "name": "dst", "function": "c:@F@escape_str", "type": { "type_name": "char *restrict", "type_usr": "", "type_is_pointer": true, "pointee_type_name": "char", "pointee_type_usr": ""} }
{ "file": "procps/build/include/proc/escape.h", "line": "18", "kind": "ParmDecl", "name": "src", "function": "c:@F@escape_str", "type": { "type_name": "const char *restrict", "type_usr": "", "type_is_pointer": true, "pointee_type_name": "const char", "pointee_type_usr": ""} }
{ "file": "procps/build/include/proc/escape.h", "line": "18", "kind": "ParmDecl", "name": "bufsize", "function": "c:@F@escape_str", "type": { "type_name": "int", "type_usr": "", "type_is_pointer": false} }
{ "file": "procps/build/include/proc/escape.h", "line": "18", "kind": "ParmDecl", "name": "maxcells", "function": "c:@F@escape_str", "type": { "type_name": "int *", "type_usr": "", "type_is_pointer": true, "pointee_type_name": "int", "pointee_type_usr": ""} }
{ "file": "procps/build/include/proc/escape.h", "line": "19", "kind": "ParmDecl", "name": "outbuf", "function": "c:@F@escape_command", "type": { "type_name": "char *const restrict", "type_usr": "", "type_is_pointer": true, "pointee_type_name": "char", "pointee_type_usr": ""} }
{ "file": "procps/build/include/proc/escape.h", "line": "19", "kind": "ParmDecl", "name": "pp", "function": "c:@F@escape_command", "type": { "type_name": "const proc_t *const restrict", "type_usr": "", "type_is_pointer": true, "pointee_type_name": "const proc_t", "pointee_type_usr": "c:readproc.h@T@proc_t"} }
{ "file": "procps/build/include/proc/escape.h", "line": "19", "kind": "ParmDecl", "name": "bytes", "function": "c:@F@escape_command", "type": { "type_name": "int", "type_usr": "", "type_is_pointer": false} }
{ "file": "procps/build/include/proc/escape.h", "line": "19", "kind": "ParmDecl", "name": "cells", "function": "c:@F@escape_command", "type": { "type_name": "int *", "type_usr": "", "type_is_pointer": true, "pointee_type_name": "int", "pointee_type_usr": ""} }
{ "file": "procps/build/include/proc/escape.h", "line": "19", "kind": "ParmDecl", "name": "flags", "function": "c:@F@escape_command", "type": { "type_name": "unsigned int", "type_usr": "", "type_is_pointer": false} }
{ "file": "procps/build/include/proc/escape.h", "line": "20", "kind": "ParmDecl", "name": "dst", "function": "c:@F@escaped_copy", "type": { "type_name": "char *restrict", "type_usr": "", "type_is_pointer": true, "pointee_type_name": "char", "pointee_type_usr": ""} }
{ "file": "procps/build/include/proc/escape.h", "line": "20", "kind": "ParmDecl", "name": "src", "function": "c:@F@escaped_copy", "type": { "type_name": "const char *restrict", "type_usr": "", "type_is_pointer": true, "pointee_type_name": "const char", "pointee_type_usr": ""} }
{ "file": "procps/build/include/proc/escape.h", "line": "20", "kind": "ParmDecl", "name": "bufsize", "function": "c:@F@escaped_copy", "type": { "type_name": "int", "type_usr": "", "type_is_pointer": false} }
{ "file": "procps/build/include/proc/escape.h", "line": "20", "kind": "ParmDecl", "name": "maxroom", "function": "c:@F@escaped_copy", "type": { "type_name": "int *", "type_usr": "", "type_is_pointer": true, "pointee_type_name": "int", "pointee_type_usr": ""} }
{ "file": "procps/build/include/proc/pwcache.h", "line": "12", "kind": "ParmDecl", "name": "uid", "function": "c:@F@pwcache_get_user", "type": { "type_name": "uid_t", "type_usr": "c:@T@uid_t", "type_is_pointer": false} }
{ "file": "procps/build/include/proc/pwcache.h", "line": "13", "kind": "ParmDecl", "name": "gid", "function": "c:@F@pwcache_get_group", "type": { "type_name": "gid_t", "type_usr": "c:@T@gid_t", "type_is_pointer": false} }
{ "file": "procps/build/include/proc/readproc.h", "line": "43", "kind": "ParmDecl", "name": "id", "function": "c:@F@get_ns_name", "type": { "type_name": "int", "type_usr": "", "type_is_pointer": false} }
{ "file": "procps/build/include/proc/readproc.h", "line": "44", "kind": "ParmDecl", "name": "name", "function": "c:@F@get_ns_id", "type": { "type_name": "const char *", "type_usr": "", "type_is_pointer": true, "pointee_type_name": "const char", "pointee_type_usr": ""} }
{ "file": "procps/build/include/proc/readproc.h", "line": "221", "kind": "ParmDecl", "name": "flags", "function": "c:@F@openproc", "type": { "type_name": "int", "type_usr": "", "type_is_pointer": false} }
{ "file": "procps/build/include/proc/readproc.h", "line": "232", "kind": "ParmDecl", "name": "want_proc", "function": "c:@F@readproctab2", "type": { "type_name": "int (*)(proc_t *)", "type_usr": "", "type_is_pointer": true, "pointee_type_name": "int (proc_t *)", "pointee_type_usr": ""} }
{ "file": "procps/build/include/proc/readproc.h", "line": "232", "kind": "ParmDecl", "name": "want_task", "function": "c:@F@readproctab2", "type": { "type_name": "int (*)(proc_t *)", "type_usr": "", "type_is_pointer": true, "pointee_type_name": "int (proc_t *)", "pointee_type_usr": ""} }
{ "file": "procps/build/include/proc/readproc.h", "line": "232", "kind": "ParmDecl", "name": "PT", "function": "c:@F@readproctab2", "type": { "type_name": "PROCTAB *const restrict", "type_usr": "", "type_is_pointer": true, "pointee_type_name": "PROCTAB", "pointee_type_usr": "c:readproc.h@T@PROCTAB"} }
{ "file": "procps/build/include/proc/readproc.h", "line": "233", "kind": "ParmDecl", "name": "want_task", "function": "c:@F@readproctab3", "type": { "type_name": "int (*)(proc_t *)", "type_usr": "", "type_is_pointer": true, "pointee_type_name": "int (proc_t *)", "pointee_type_usr": ""} }
{ "file": "procps/build/include/proc/readproc.h", "line": "233", "kind": "ParmDecl", "name": "PT", "function": "c:@F@readproctab3", "type": { "type_name": "PROCTAB *const restrict", "type_usr": "", "type_is_pointer": true, "pointee_type_name": "PROCTAB", "pointee_type_usr": "c:readproc.h@T@PROCTAB"} }
{ "file": "procps/build/include/proc/readproc.h", "line": "239", "kind": "ParmDecl", "name": "flags", "function": "c:@F@readproctab", "type": { "type_name": "int", "type_usr": "", "type_is_pointer": false} }
{ "file": "procps/build/include/proc/readproc.h", "line": "242", "kind": "ParmDecl", "name": "PT", "function": "c:@F@closeproc", "type": { "type_name": "PROCTAB *", "type_usr": "", "type_is_pointer": true, "pointee_type_name": "PROCTAB", "pointee_type_usr": "c:readproc.h@T@PROCTAB"} }
{ "file": "procps/build/include/proc/readproc.h", "line": "254", "kind": "ParmDecl", "name": "PT", "function": "c:@F@readproc", "type": { "type_name": "PROCTAB *const restrict", "type_usr": "", "type_is_pointer": true, "pointee_type_name": "PROCTAB", "pointee_type_usr": "c:readproc.h@T@PROCTAB"} }
{ "file": "procps/build/include/proc/readproc.h", "line": "254", "kind": "ParmDecl", "name": "p", "function": "c:@F@readproc", "type": { "type_name": "proc_t *restrict", "type_usr": "", "type_is_pointer": true, "pointee_type_name": "proc_t", "pointee_type_usr": "c:readproc.h@T@proc_t"} }
{ "file": "procps/build/include/proc/readproc.h", "line": "255", "kind": "ParmDecl", "name": "PT", "function": "c:@F@readtask", "type": { "type_name": "PROCTAB *const restrict", "type_usr": "", "type_is_pointer": true, "pointee_type_name": "PROCTAB", "pointee_type_usr": "c:readproc.h@T@PROCTAB"} }
{ "file": "procps/build/include/proc/readproc.h", "line": "255", "kind": "ParmDecl", "name": "p", "function": "c:@F@readtask", "type": { "type_name": "const proc_t *const restrict", "type_usr": "", "type_is_pointer": true, "pointee_type_name": "const proc_t", "pointee_type_usr": "c:readproc.h@T@proc_t"} }
{ "file": "procps/build/include/proc/readproc.h", "line": "255", "kind": "ParmDecl", "name": "t", "function": "c:@F@readtask", "type": { "type_name": "proc_t *restrict", "type_usr": "", "type_is_pointer": true, "pointee_type_name": "proc_t", "pointee_type_usr": "c:readproc.h@T@proc_t"} }
{ "file": "procps/build/include/proc/readproc.h", "line": "256", "kind": "ParmDecl", "name": "PT", "function": "c:@F@readeither", "type": { "type_name": "PROCTAB *const restrict", "type_usr": "", "type_is_pointer": true, "pointee_type_name": "PROCTAB", "pointee_type_usr": "c:readproc.h@T@PROCTAB"} }
{ "file": "procps/build/include/proc/readproc.h", "line": "256", "kind": "ParmDecl", "name": "x", "function": "c:@F@readeither", "type": { "type_name": "proc_t *restrict", "type_usr": "", "type_is_pointer": true, "pointee_type_name": "proc_t", "pointee_type_usr": "c:readproc.h@T@proc_t"} }
{ "file": "procps/build/include/proc/readproc.h", "line": "259", "kind": "ParmDecl", "name": "dst", "function": "c:@F@read_cmdline", "type": { "type_name": "char *const restrict", "type_usr": "", "type_is_pointer": true, "pointee_type_name": "char", "pointee_type_usr": ""} }
{ "file": "procps/build/include/proc/readproc.h", "line": "259", "kind": "ParmDecl", "name": "sz", "function": "c:@F@read_cmdline", "type": { "type_name": "unsigned int", "type_usr": "", "type_is_pointer": false} }
{ "file": "procps/build/include/proc/readproc.h", "line": "259", "kind": "ParmDecl", "name": "pid", "function": "c:@F@read_cmdline", "type": { "type_name": "unsigned int", "type_usr": "", "type_is_pointer": false} }
{ "file": "procps/build/include/proc/readproc.h", "line": "261", "kind": "ParmDecl", "name": "p", "function": "c:@F@look_up_our_self", "type": { "type_name": "proc_t *", "type_usr": "", "type_is_pointer": true, "pointee_type_name": "proc_t", "pointee_type_usr": "c:readproc.h@T@proc_t"} }
{ "file": "procps/build/include/proc/readproc.h", "line": "264", "kind": "ParmDecl", "name": "p", "function": "c:@F@freeproc", "type": { "type_name": "proc_t *", "type_usr": "", "type_is_pointer": true, "pointee_type_name": "proc_t", "pointee_type_usr": "c:readproc.h@T@proc_t"} }
{ "file": "procps/build/include/proc/readproc.h", "line": "267", "kind": "ParmDecl", "name": "pid", "function": "c:@F@get_proc_stats", "type": { "type_name": "pid_t", "type_usr": "c:@T@pid_t", "type_is_pointer": false} }
{ "file": "procps/build/include/proc/readproc.h", "line": "267", "kind": "ParmDecl", "name": "p", "function": "c:@F@get_proc_stats", "type": { "type_name": "proc_t *", "type_usr": "", "type_is_pointer": true, "pointee_type_name": "proc_t", "pointee_type_usr": "c:readproc.h@T@proc_t"} }
{ "file": "procps/build/include/proc/sig.h", "line": "19", "kind": "ParmDecl", "name": "name", "function": "c:@F@signal_name_to_number", "type": { "type_name": "const char *restrict", "type_usr": "", "type_is_pointer": true, "pointee_type_name": "const char", "pointee_type_usr": ""} }
{ "file": "procps/build/include/proc/sig.h", "line": "21", "kind": "ParmDecl", "name": "signo", "function": "c:@F@signal_number_to_name", "type": { "type_name": "int", "type_usr": "", "type_is_pointer": false} }
{ "file": "procps/build/include/proc/sig.h", "line": "23", "kind": "ParmDecl", "name": "argc", "function": "c:@F@print_given_signals", "type": { "type_name": "int", "type_usr": "", "type_is_pointer": false} }
{ "file": "procps/build/include/proc/sig.h", "line": "23", "kind": "ParmDecl", "name": "argv", "function": "c:@F@print_given_signals", "type": { "type_name": "const char *const restrict *restrict", "type_usr": "", "type_is_pointer": true, "pointee_type_name": "const char *const restrict", "pointee_type_usr": ""} }
{ "file": "procps/build/include/proc/sig.h", "line": "23", "kind": "ParmDecl", "name": "max_line", "function": "c:@F@print_given_signals", "type": { "type_name": "int", "type_usr": "", "type_is_pointer": false} }
{ "file": "procps/build/include/proc/sig.h", "line": "25", "kind": "ParmDecl", "name": "s", "function": "c:@F@strtosig", "type": { "type_name": "const char *restrict", "type_usr": "", "type_is_pointer": true, "pointee_type_name": "const char", "pointee_type_usr": ""} }
{ "file": "procps/build/include/proc/slab.h", "line": "35", "kind": "ParmDecl", "name": "", "function": "c:@F@put_slabinfo", "type": { "type_name": "struct slab_info *", "type_usr": "", "type_is_pointer": true, "pointee_type_name": "struct slab_info", "pointee_type_usr": "c:@S@slab_info"} }
{ "file": "procps/build/include/proc/slab.h", "line": "36", "kind": "ParmDecl", "name": "", "function": "c:@F@free_slabinfo", "type": { "type_name": "struct slab_info *", "type_usr": "", "type_is_pointer": true, "pointee_type_name": "struct slab_info", "pointee_type_usr": "c:@S@slab_info"} }
{ "file": "procps/build/include/proc/slab.h", "line": "37", "kind": "ParmDecl", "name": "", "function": "c:@F@get_slabinfo", "type": { "type_name": "struct slab_info **", "type_usr": "", "type_is_pointer": true, "pointee_type_name": "struct slab_info *", "pointee_type_usr": ""} }
{ "file": "procps/build/include/proc/slab.h", "line": "37", "kind": "ParmDecl", "name": "", "function": "c:@F@get_slabinfo", "type": { "type_name": "struct slab_stat *", "type_usr": "", "type_is_pointer": true, "pointee_type_name": "struct slab_stat", "pointee_type_usr": "c:@S@slab_stat"} }
{ "file": "procps/build/include/proc/sysinfo.h", "line": "20", "kind": "ParmDecl", "name": "uptime_secs", "function": "c:@F@uptime", "type": { "type_name": "double *", "type_usr": "", "type_is_pointer": true, "pointee_type_name": "double", "pointee_type_usr": ""} }
{ "file": "procps/build/include/proc/sysinfo.h", "line": "20", "kind": "ParmDecl", "name": "idle_secs", "function": "c:@F@uptime", "type": { "type_name": "double *", "type_usr": "", "type_is_pointer": true, "pointee_type_name": "double", "pointee_type_usr": ""} }
{ "file": "procps/build/include/proc/sysinfo.h", "line": "22", "kind": "ParmDecl", "name": "av1", "function": "c:@F@loadavg", "type": { "type_name": "double *", "type_usr": "", "type_is_pointer": true, "pointee_type_name": "double", "pointee_type_usr": ""} }
{ "file": "procps/build/include/proc/sysinfo.h", "line": "22", "kind": "ParmDecl", "name": "av5", "function": "c:@F@loadavg", "type": { "type_name": "double *", "type_usr": "", "type_is_pointer": true, "pointee_type_name": "double", "pointee_type_usr": ""} }
{ "file": "procps/build/include/proc/sysinfo.h", "line": "22", "kind": "ParmDecl", "name": "av15", "function": "c:@F@loadavg", "type": { "type_name": "double *", "type_usr": "", "type_is_pointer": true, "pointee_type_name": "double", "pointee_type_usr": ""} }
{ "file": "procps/build/include/proc/sysinfo.h", "line": "61", "kind": "ParmDecl", "name": "cuse", "function": "c:@F@getstat", "type": { "type_name": "jiff *restrict", "type_usr": "", "type_is_pointer": true, "pointee_type_name": "jiff", "pointee_type_usr": "c:sysinfo.h@T@jiff"} }
{ "file": "procps/build/include/proc/sysinfo.h", "line": "61", "kind": "ParmDecl", "name": "cice", "function": "c:@F@getstat", "type": { "type_name": "jiff *restrict", "type_usr": "", "type_is_pointer": true, "pointee_type_name": "jiff", "pointee_type_usr": "c:sysinfo.h@T@jiff"} }
{ "file": "procps/build/include/proc/sysinfo.h", "line": "61", "kind": "ParmDecl", "name": "csys", "function": "c:@F@getstat", "type": { "type_name": "jiff *restrict", "type_usr": "", "type_is_pointer": true, "pointee_type_name": "jiff", "pointee_type_usr": "c:sysinfo.h@T@jiff"} }
{ "file": "procps/build/include/proc/sysinfo.h", "line": "61", "kind": "ParmDecl", "name": "cide", "function": "c:@F@getstat", "type": { "type_name": "jiff *restrict", "type_usr": "", "type_is_pointer": true, "pointee_type_name": "jiff", "pointee_type_usr": "c:sysinfo.h@T@jiff"} }
{ "file": "procps/build/include/proc/sysinfo.h", "line": "61", "kind": "ParmDecl", "name": "ciow", "function": "c:@F@getstat", "type": { "type_name": "jiff *restrict", "type_usr": "", "type_is_pointer": true, "pointee_type_name": "jiff", "pointee_type_usr": "c:sysinfo.h@T@jiff"} }
{ "file": "procps/build/include/proc/sysinfo.h", "line": "61", "kind": "ParmDecl", "name": "cxxx", "function": "c:@F@getstat", "type": { "type_name": "jiff *restrict", "type_usr": "", "type_is_pointer": true, "pointee_type_name": "jiff", "pointee_type_usr": "c:sysinfo.h@T@jiff"} }
{ "file": "procps/build/include/proc/sysinfo.h", "line": "61", "kind": "ParmDecl", "name": "cyyy", "function": "c:@F@getstat", "type": { "type_name": "jiff *restrict", "type_usr": "", "type_is_pointer": true, "pointee_type_name": "jiff", "pointee_type_usr": "c:sysinfo.h@T@jiff"} }
{ "file": "procps/build/include/proc/sysinfo.h", "line": "61", "kind": "ParmDecl", "name": "czzz", "function": "c:@F@getstat", "type": { "type_name": "jiff *restrict", "type_usr": "", "type_is_pointer": true, "pointee_type_name": "jiff", "pointee_type_usr": "c:sysinfo.h@T@jiff"} }
{ "file": "procps/build/include/proc/sysinfo.h", "line": "62", "kind": "ParmDecl", "name": "pin", "function": "c:@F@getstat", "type": { "type_name": "unsigned long *restrict", "type_usr": "", "type_is_pointer": true, "pointee_type_name": "unsigned long", "pointee_type_usr": ""} }
{ "file": "procps/build/include/proc/sysinfo.h", "line": "62", "kind": "ParmDecl", "name": "pout", "function": "c:@F@getstat", "type": { "type_name": "unsigned long *restrict", "type_usr": "", "type_is_pointer": true, "pointee_type_name": "unsigned long", "pointee_type_usr": ""} }
{ "file": "procps/build/include/proc/sysinfo.h", "line": "62", "kind": "ParmDecl", "name": "s_in", "function": "c:@F@getstat", "type": { "type_name": "unsigned long *restrict", "type_usr": "", "type_is_pointer": true, "pointee_type_name": "unsigned long", "pointee_type_usr": ""} }
{ "file": "procps/build/include/proc/sysinfo.h", "line": "62", "kind": "ParmDecl", "name": "sout", "function": "c:@F@getstat", "type": { "type_name": "unsigned long *restrict", "type_usr": "", "type_is_pointer": true, "pointee_type_name": "unsigned long", "pointee_type_usr": ""} }
{ "file": "procps/build/include/proc/sysinfo.h", "line": "63", "kind": "ParmDecl", "name": "intr", "function": "c:@F@getstat", "type": { "type_name": "unsigned int *restrict", "type_usr": "", "type_is_pointer": true, "pointee_type_name": "unsigned int", "pointee_type_usr": ""} }
{ "file": "procps/build/include/proc/sysinfo.h", "line": "63", "kind": "ParmDecl", "name": "ctxt", "function": "c:@F@getstat", "type": { "type_name": "unsigned int *restrict", "type_usr": "", "type_is_pointer": true, "pointee_type_name": "unsigned int", "pointee_type_usr": ""} }
{ "file": "procps/build/include/proc/sysinfo.h", "line": "64", "kind": "ParmDecl", "name": "running", "function": "c:@F@getstat", "type": { "type_name": "unsigned int *restrict", "type_usr": "", "type_is_pointer": true, "pointee_type_name": "unsigned int", "pointee_type_usr": ""} }
{ "file": "procps/build/include/proc/sysinfo.h", "line": "64", "kind": "ParmDecl", "name": "blocked", "function": "c:@F@getstat", "type": { "type_name": "unsigned int *restrict", "type_usr": "", "type_is_pointer": true, "pointee_type_name": "unsigned int", "pointee_type_usr": ""} }
{ "file": "procps/build/include/proc/sysinfo.h", "line": "65", "kind": "ParmDecl", "name": "btime", "function": "c:@F@getstat", "type": { "type_name": "unsigned int *restrict", "type_usr": "", "type_is_pointer": true, "pointee_type_name": "unsigned int", "pointee_type_usr": ""} }
{ "file": "procps/build/include/proc/sysinfo.h", "line": "65", "kind": "ParmDecl", "name": "processes", "function": "c:@F@getstat", "type": { "type_name": "unsigned int *restrict", "type_usr": "", "type_is_pointer": true, "pointee_type_name": "unsigned int", "pointee_type_usr": ""} }
{ "file": "procps/build/include/proc/sysinfo.h", "line": "126", "kind": "ParmDecl", "name": "disks", "function": "c:@F@getpartitions_num", "type": { "type_name": "struct disk_stat *", "type_usr": "", "type_is_pointer": true, "pointee_type_name": "struct disk_stat", "pointee_type_usr": "c:@S@disk_stat"} }
{ "file": "procps/build/include/proc/sysinfo.h", "line": "126", "kind": "ParmDecl", "name": "ndisks", "function": "c:@F@getpartitions_num", "type": { "type_name": "int", "type_usr": "", "type_is_pointer": false} }
{ "file": "procps/build/include/proc/sysinfo.h", "line": "127", "kind": "ParmDecl", "name": "", "function": "c:@F@getdiskstat", "type": { "type_name": "struct disk_stat **", "type_usr": "", "type_is_pointer": true, "pointee_type_name": "struct disk_stat *", "pointee_type_usr": ""} }
{ "file": "procps/build/include/proc/sysinfo.h", "line": "127", "kind": "ParmDecl", "name": "", "function": "c:@F@getdiskstat", "type": { "type_name": "struct partition_stat **", "type_usr": "", "type_is_pointer": true, "pointee_type_name": "struct partition_stat *", "pointee_type_usr": ""} }
{ "file": "procps/build/include/proc/sysinfo.h", "line": "137", "kind": "ParmDecl", "name": "", "function": "c:@F@getslabinfo", "type": { "type_name": "struct slab_cache **", "type_usr": "", "type_is_pointer": true, "pointee_type_name": "struct slab_cache *", "pointee_type_usr": ""} }
{ "file": "procps/build/include/proc/wchan.h", "line": "8", "kind": "ParmDecl", "name": "pid", "function": "c:@F@lookup_wchan", "type": { "type_name": "int", "type_usr": "", "type_is_pointer": false} }
{ "file": "procps/build/include/proc/whattime.h", "line": "8", "kind": "ParmDecl", "name": "human_readable", "function": "c:@F@print_uptime", "type": { "type_name": "int", "type_usr": "", "type_is_pointer": false} }
{ "file": "procps/build/include/proc/whattime.h", "line": "9", "kind": "ParmDecl", "name": "human_readable", "function": "c:@F@sprint_uptime", "type": { "type_name": "int", "type_usr": "", "type_is_pointer": false} }
